comum
tests
