Metadata-Version: 1.1
Name: django-comum
Version: 1.0.3
Summary: Pluggable django app for commom models and utilities.
Home-page: https://gitlab.sigmageosistemas.com.br/dev/django-usuarios/
Author: SIGMA Geosistemas
Author-email: atendimento@consultoriasigma.com.br
License: UNKNOWN
Platform: UNKNOWN
Classifier: Framework :: Django
Classifier: Development Status :: 5 - Production/Stable
Classifier: Environment :: Web Environment
Classifier: Intended Audience :: Developers
Classifier: License :: OSI Approved :: MIT License
Classifier: Operating System :: OS Independent
Classifier: Programming Language :: Python
Classifier: Topic :: Utilities
Classifier: Natural Language :: Portuguese (Brazilian)
